{"cameraMode":{"drawMode":0,"name":"Shaded","section":"Shading Mode"},"sceneLighting":true,"audioPlay":false,"sceneViewState":{"m_AlwaysRefresh":false,"showFog":true,"showSkybox":false,"showFlares":true,"showImageEffects":true,"showParticleSystems":true,"showVisualEffectGraphs":true,"m_FxEnabled":true},"in2DMode":false,"pivot":{"x":-0.2636679410934448,"y":0.6454384326934815,"z":0.4523444175720215},"rotation":{"x":-0.03482472896575928,"y":0.965798556804657,"z":-0.17446419596672059,"w":-0.1899845153093338},"size":2.293475866317749,"orthographic":false}